[{
  "_id": {
    "$oid": "673037fae7b56bcadce632e2"
  },
  "user_id": 1,
  "company": "HCL",
  "drive_date": {
    "$date": "2024-10-11T18:30:00.000Z"
  }
},
{
  "_id": {
    "$oid": "673037fae7b56bcadce632e3"
  },
  "user_id": 2,
  "company": "HCL",
  "drive_date": {
    "$date": "2024-10-11T18:30:00.000Z"
  }
},
{
  "_id": {
    "$oid": "673037fae7b56bcadce632e4"
  },
  "user_id": 3,
  "company": "HCL",
  "drive_date": {
    "$date": "2024-10-11T18:30:00.000Z"
  }
},
{
  "_id": {
    "$oid": "673037fae7b56bcadce632e5"
  },
  "user_id": 4,
  "company": "HCL",
  "drive_date": {
    "$date": "2024-10-11T18:30:00.000Z"
  }
},
{
  "_id": {
    "$oid": "673037fae7b56bcadce632e6"
  },
  "user_id": 5,
  "company": "TCS",
  "drive_date": {
    "$date": "2024-10-24T18:30:00.000Z"
  }
},
{
  "_id": {
    "$oid": "673037fae7b56bcadce632e7"
  },
  "user_id": 6,
  "company": "TCS",
  "drive_date": {
    "$date": "2024-10-24T18:30:00.000Z"
  }
},
{
  "_id": {
    "$oid": "673037fae7b56bcadce632e8"
  },
  "user_id": 7,
  "company": "TCS",
  "drive_date": {
    "$date": "2024-10-24T18:30:00.000Z"
  }
},
{
  "_id": {
    "$oid": "673037fae7b56bcadce632e9"
  },
  "user_id": 8,
  "company": "TCS",
  "drive_date": {
    "$date": "2024-10-24T18:30:00.000Z"
  }
},
{
  "_id": {
    "$oid": "673037fae7b56bcadce632ea"
  },
  "user_id": 9,
  "company": "WIPRO",
  "drive_date": {
    "$date": "2024-10-28T18:30:00.000Z"
  }
},
{
  "_id": {
    "$oid": "673037fae7b56bcadce632eb"
  },
  "user_id": 10,
  "company": "WIPRO",
  "drive_date": {
    "$date": "2024-10-28T18:30:00.000Z"
  }
},
{
  "_id": {
    "$oid": "673037fae7b56bcadce632ec"
  },
  "user_id": 11,
  "company": "WIPRO",
  "drive_date": {
    "$date": "2024-10-28T18:30:00.000Z"
  }
},
{
  "_id": {
    "$oid": "673037fae7b56bcadce632ed"
  },
  "user_id": 12,
  "company": "WIPRO",
  "drive_date": {
    "$date": "2024-10-28T18:30:00.000Z"
  }
}]